README
setup.py
odeViz/__init__.py
odeViz/ode_objects.py
odeViz/ode_visualization.py
odeViz.egg-info/PKG-INFO
odeViz.egg-info/SOURCES.txt
odeViz.egg-info/dependency_links.txt
odeViz.egg-info/requires.txt
odeViz.egg-info/top_level.txt