Metadata-Version: 1.1
Name: odeViz
Version: 0.2
Summary: This toolbox generates automatically a vtk-visualization for an ode (Open Dynamics Engine) simulation under Python. You only have to define the simulation space and world and forward these entities to the visualization.
Home-page: https://pypi.python.org/pypi/ode-viz
Author: André Dietrich
Author-email: dietrich@ivs.cs.uni-magdeburg.de
License: BSD
Keywords: ode,vtk
Platform: UNKNOWN
Classifier: Development Status :: 3 - Alpha
Classifier: Topic :: Utilities
Classifier: License :: OSI Approved :: BSD License
